in_addr_arpa.py
in_addr_arpa-0.1.dist-info/entry_points.txt
in_addr_arpa-0.1.dist-info/licenses/LICENSE
in_addr_arpa-0.1.dist-info/WHEEL
in_addr_arpa-0.1.dist-info/METADATA
in_addr_arpa-0.1.dist-info/RECORD
