Metadata-Version: 2.4
Name: in_addr_arpa
Version: 0.1
Summary: Do reverse DNS query on networks.
Author-email: Julien Palard <julien@palard.fr>
License-Expression: MIT
License-File: LICENSE
Project-URL: Home, https://git.afpy.org/mdk/in_addr_arpa
